pika_api/__init__.py
pika_api/exceptions.py
pika_api/sdk.py
pika_api-0.1.0.dist-info/LICENSE
pika_api-0.1.0.dist-info/METADATA
pika_api-0.1.0.dist-info/WHEEL
pika_api-0.1.0.dist-info/top_level.txt
pika_api-0.1.0.dist-info/RECORD
