Metadata-Version: 2.1
Name: pika-api
Version: 0.1.0
Summary: Pika API python SDK.
Author-email: Rishi Mohan <iamrishi.ms@gmail.com>
License: MIT License
Project-URL: Homepage, https://github.com/rishimohan/pika-api-python-sdk
Classifier: License :: OSI Approved :: MIT License
Classifier: Programming Language :: Python
Classifier: Programming Language :: Python :: 3
Requires-Python: >=3.6
License-File: LICENSE
Requires-Dist: requests >=2.28.1
